odoo/addons/stock_release_channel_plan/README.rst
odoo/addons/stock_release_channel_plan/__init__.py
odoo/addons/stock_release_channel_plan/__manifest__.py
odoo/addons/stock_release_channel_plan/demo/stock_release_channel.xml
odoo/addons/stock_release_channel_plan/demo/stock_release_channel_preparation_plan.xml
odoo/addons/stock_release_channel_plan/i18n/fr.po
odoo/addons/stock_release_channel_plan/i18n/it.po
odoo/addons/stock_release_channel_plan/i18n/stock_release_channel_plan.pot
odoo/addons/stock_release_channel_plan/models/__init__.py
odoo/addons/stock_release_channel_plan/models/res_partner.py
odoo/addons/stock_release_channel_plan/models/stock_release_channel.py
odoo/addons/stock_release_channel_plan/models/stock_release_channel_preparation_plan.py
odoo/addons/stock_release_channel_plan/readme/CONFIGURE.md
odoo/addons/stock_release_channel_plan/readme/CONTRIBUTORS.md
odoo/addons/stock_release_channel_plan/readme/CREDITS.md
odoo/addons/stock_release_channel_plan/readme/DESCRIPTION.md
odoo/addons/stock_release_channel_plan/readme/USAGE.md
odoo/addons/stock_release_channel_plan/security/stock_release_channel_plan_launch.xml
odoo/addons/stock_release_channel_plan/security/stock_release_channel_preparation_plan.xml
odoo/addons/stock_release_channel_plan/static/description/icon.png
odoo/addons/stock_release_channel_plan/static/description/index.html
odoo/addons/stock_release_channel_plan/tests/__init__.py
odoo/addons/stock_release_channel_plan/tests/common.py
odoo/addons/stock_release_channel_plan/tests/test_stock_release_channel_plan.py
odoo/addons/stock_release_channel_plan/views/res_partner.xml
odoo/addons/stock_release_channel_plan/views/stock_release_channel.xml
odoo/addons/stock_release_channel_plan/views/stock_release_channel_preparation_plan.xml
odoo/addons/stock_release_channel_plan/wizards/__init__.py
odoo/addons/stock_release_channel_plan/wizards/launch_plan.py
odoo/addons/stock_release_channel_plan/wizards/launch_plan.xml
odoo_addon_stock_release_channel_plan-18.0.1.1.0.dist-info/METADATA
odoo_addon_stock_release_channel_plan-18.0.1.1.0.dist-info/WHEEL
odoo_addon_stock_release_channel_plan-18.0.1.1.0.dist-info/top_level.txt
odoo_addon_stock_release_channel_plan-18.0.1.1.0.dist-info/RECORD
